{
  "BSI0001": [7.8, 9.1, 6.5],
  "BSI0002": [8.4, 5.2, 7.9],
  "BSI0003": [6.7, 8.8, 9.5],
  "BSI0005": [5.0, 7.2, 8.3, 6.0],
  "CORI0082": [9.4, 6.2, 8.0],

  "BSI0006": [7.0, 7.5, 8.4, 6.9],
  "BSI0007": [9.3, 8.2, 7.8],
  "BSI0008": [6.5, 9.1, 8.0],
  "BSI0009": [4.0, 6.5, 7.2, 5.5],
  "BSI0010": [8.8, 7.4, 6.9],

  "CORI0040": [6.3, 4.5, 8.0, 7.2],
  "CORI0041": [10.0, 8.5, 7.0],
  "CORI0042": [5.0, 9.0, 6.5, 8.8],
  "CORI0043": [8.2, 9.4, 7.1],
  "CORI0048": [6.0, 7.5, 4.0],

  "CORI0049": [8.4, 7.3, 6.0],
  "CORI0050": [9.7, 10.0, 8.8],
  "CORI0051": [6.8, 8.2, 9.0],
  "CORI0052": [5.0, 4.0, 7.2],
  "CORI0053": [8.5, 9.3, 7.7],

  "CORI0054": [9.0, 7.1, 6.0],
  "CORI0055": [8.7, 9.5, 7.2],
  "CORI0056": [6.3, 8.8, 9.9],
  "CORI0057": [9.5, 10.0, 7.4],
  "CORI0058": [7.0, 8.0, 8.9],

  "CORI0059": [6.5, 9.0, 7.5],
  "CORI0060": [8.0, 8.3, 6.2],
  "CORI0061": [7.7, 9.1, 8.0],
  "CORI0062": [6.4, 9.5, 7.2, 8.3],
  "CORI0063": [9.0, 8.8, 7.0],

  "CORI0064": [7.5, 6.3, 8.5],
  "CORI0066": [9.1, 7.2, 8.9],
  "CORI0067": [6.0, 8.0, 7.5],
  "CORI0068": [8.8, 9.3, 7.1],
  "CORI0069": [7.0, 10.0, 8.5],
  "CORI0075": [9.0, 9.8, 8.3],

  "CORI0070": [8.0, 7.7],
  "CORI0072": [9.3, 8.5, 7.4],
  "CORI0073": [7.0, 8.8, 9.0],
  "CORI0074": [9.9, 8.2, 7.5],
  "CORI0078": [10.0, 9.7, 8.3],
  "CORI0079": [9.0, 9.5, 10.0],
  "CORI0080": [8.8, 9.3, 9.9],

  "ENADE-I": [10.0],
  "ENADE-C": [10.0]
}
